[
  {
    "id": 2,
    "restaurantName": "必胜客",
    "dishName": "单人套餐",
    "tags": [],
    "imageUrl": "/images/default-dish.jpg",
    "description": "",
    "userId": "user_001",
    "userName": "当前用户",
    "createdAt": "2025-09-12T14:45:35.349Z"
  },
  {
    "id": 5,
    "restaurantName": "麦当劳",
    "dishName": "辣翅",
    "tags": [],
    "imageUrl": "/images/default-dish.jpg",
    "description": "",
    "userId": "on_285bdf6fad75b9729ee1b79d04661c55",
    "userName": "gavin",
    "createdAt": "2025-09-29T02:59:34.926Z"
  },
  {
    "id": 6,
    "restaurantName": "健康餐",
    "dishName": "健康",
    "tags": [],
    "imageUrl": "/images/default-dish.jpg",
    "description": "！！！",
    "userId": "on_bf89e2a0c949adfcbb5a33c66856a3a3",
    "userName": "Sonny",
    "createdAt": "2025-10-10T08:10:32.942Z"
  },
  {
    "id": 7,
    "restaurantName": "必胜客",
    "dishName": "pizza",
    "tags": [],
    "imageUrl": "/uploads/submissions/submission-1760880204704-472306515.jpeg",
    "description": "",
    "userId": "on_14f113d8579bbc6bda6afdbf0a93b6ec",
    "userName": "张雪岩",
    "createdAt": "2025-10-19T13:23:29.101Z"
  }
]
